{"cameraMode":{"drawMode":0,"name":"Shaded","section":"Shading Mode"},"sceneLighting":true,"audioPlay":false,"sceneViewState":{"m_AlwaysRefresh":false,"showFog":true,"showSkybox":true,"showFlares":true,"showImageEffects":true,"showParticleSystems":true,"showVisualEffectGraphs":true,"m_FxEnabled":true},"in2DMode":false,"pivot":{"x":-4.743206024169922,"y":-6.427543640136719,"z":0.6776752471923828},"rotation":{"x":-0.3602045178413391,"y":0.13007280230522157,"z":-0.05079612135887146,"w":-0.9223648309707642},"size":7.801235198974609,"orthographic":false}